CHANGES.txt
MANIFEST.in
README.txt
setup.py
src/connpass/__init__.py
src/connpass/__main__.py
src/connpass/commands.py
src/python_connpass.egg-info/PKG-INFO
src/python_connpass.egg-info/SOURCES.txt
src/python_connpass.egg-info/dependency_links.txt
src/python_connpass.egg-info/entry_points.txt
src/python_connpass.egg-info/requires.txt
src/python_connpass.egg-info/top_level.txt